<?xml version="1.0" encoding="UTF-8" standalone="no"?>
<ESPN_EVENT>
  <gameID>401721243</gameID>
  <visitor>Alabama A&amp;M Bulldogs</visitor>
  <home>Bethune-Cookman Wildcats</home>
  <date>20250203</date>
  <ESPN_DATA_PARSE_VERSION>20250203</ESPN_DATA_PARSE_VERSION>
  <ESPN_BOX_URL>https://www.espn.com/mens-college-basketball/game/_/gameId/401721243/alabama-am-bethune</ESPN_BOX_URL>
  <RESULT>
    <visitor>
      <id>2010</id>
      <team_long>Alabama A&amp;M Bulldogs</team_long>
      <team_short>Aamu</team_short>
      <T>75</T>
      <score>(0-0)</score>
    </visitor>
    <home>
      <id>2065</id>
      <team_long>Bethune-Cookman Wildcats</team_long>
      <team_short>Bcu</team_short>
      <T>89</T>
      <score>(0-0)</score>
    </home>
  </RESULT>
  <GAME_TIME_AND_LOCATION>
    <date>20250203</date>
    <unix_time>1738627200</unix_time>
    <location>Moore Gymnasium (FL), Daytona Beach, FL</location>
    <attendance>Attendance: 993</attendance>
    <capacity></capacity>
  </GAME_TIME_AND_LOCATION>
  <LINESCORE>
    <visitor>
      <id></id>
      <team_long>Alabama A&amp;M Bulldogs</team_long>
      <c1>41</c1>
      <c2>34</c2>
      <T>75</T>
    </visitor>
    <home>
      <id></id>
      <team_long>Bethune-Cookman Wildcats</team_long>
      <c1>41</c1>
      <c2>48</c2>
      <T>89</T>
    </home>
  </LINESCORE>
  <GAME_NOTES>
    <top_performers>
      <assists>
        <home>
          <player>
            <player_name>seneca-willoughby</player_name>
            <player_ID>5178200</player_ID>
            <ast>12</ast>
            <to>1</to>
            <min>36</min>
          </player>
        </home>
        <visitor>
          <player>
            <player_name>quincy-mcgriff</player_name>
            <player_ID>5105886</player_ID>
            <ast>5</ast>
            <to>1</to>
            <min>32</min>
          </player>
        </visitor>
      </assists>
      <points>
        <home>
          <player>
            <player_name>trey-thomas</player_name>
            <player_ID>5106699</player_ID>
            <pts>24</pts>
            <fg>7/21</fg>
            <ft>9/10</ft>
          </player>
        </home>
        <visitor>
          <player>
            <player_name>chad-moodie</player_name>
            <player_ID>5177526</player_ID>
            <pts>19</pts>
            <fg>9/12</fg>
            <ft>1/1</ft>
          </player>
        </visitor>
      </points>
      <rebounds>
        <home>
          <player>
            <player_name>jesus-carralero-martin</player_name>
            <player_ID>4592654</player_ID>
            <reb>11</reb>
            <dreb>9</dreb>
            <oreb>2</oreb>
          </player>
        </home>
        <visitor>
          <player>
            <player_name>chad-moodie</player_name>
            <player_ID>5177526</player_ID>
            <reb>7</reb>
            <dreb>5</dreb>
            <oreb>2</oreb>
          </player>
        </visitor>
      </rebounds>
    </top_performers>
  </GAME_NOTES>
  <STATS>
    <visitor>
      <team>Alabama A&amp;M Bulldogs</team>
      <starters>
        <player>
          <player_name>chad-moodie</player_name>
          <player_jersey>23</player_jersey>
          <pos>F</pos>
          <player_ID>5177526</player_ID>
          <MIN>25</MIN>
          <FGM-A>9-12</FGM-A>
          <_3PM-A>0-0</_3PM-A>
          <FTM-A>1-1</FTM-A>
          <OREB>2</OREB>
          <DREB>5</DREB>
          <REB>7</REB>
          <AST>2</AST>
          <STL>1</STL>
          <BLK>6</BLK>
          <TO>3</TO>
          <PF>2</PF>
          <PTS>19</PTS>
        </player>
        <player>
          <player_name>clance-crosby</player_name>
          <player_jersey>21</player_jersey>
          <pos>F</pos>
          <player_ID>5177522</player_ID>
          <MIN>13</MIN>
          <FGM-A>1-2</FGM-A>
          <_3PM-A>0-0</_3PM-A>
          <FTM-A>0-0</FTM-A>
          <OREB>0</OREB>
          <DREB>1</DREB>
          <REB>1</REB>
          <AST>0</AST>
          <STL>1</STL>
          <BLK>0</BLK>
          <TO>0</TO>
          <PF>1</PF>
          <PTS>2</PTS>
        </player>
        <player>
          <player_name>ac-bryant</player_name>
          <player_jersey>0</player_jersey>
          <pos>G</pos>
          <player_ID>5177521</player_ID>
          <MIN>15</MIN>
          <FGM-A>5-7</FGM-A>
          <_3PM-A>2-2</_3PM-A>
          <FTM-A>2-2</FTM-A>
          <OREB>1</OREB>
          <DREB>1</DREB>
          <REB>2</REB>
          <AST>1</AST>
          <STL>0</STL>
          <BLK>0</BLK>
          <TO>0</TO>
          <PF>0</PF>
          <PTS>14</PTS>
        </player>
        <player>
          <player_name>quincy-mcgriff</player_name>
          <player_jersey>4</player_jersey>
          <pos>G</pos>
          <player_ID>5105886</player_ID>
          <MIN>32</MIN>
          <FGM-A>1-6</FGM-A>
          <_3PM-A>0-4</_3PM-A>
          <FTM-A>0-0</FTM-A>
          <OREB>2</OREB>
          <DREB>2</DREB>
          <REB>4</REB>
          <AST>5</AST>
          <STL>2</STL>
          <BLK>0</BLK>
          <TO>1</TO>
          <PF>1</PF>
          <PTS>2</PTS>
        </player>
        <player>
          <player_name>london-riley</player_name>
          <player_jersey>5</player_jersey>
          <pos>G</pos>
          <player_ID>4703107</player_ID>
          <MIN>17</MIN>
          <FGM-A>1-3</FGM-A>
          <_3PM-A>1-2</_3PM-A>
          <FTM-A>2-2</FTM-A>
          <OREB>0</OREB>
          <DREB>0</DREB>
          <REB>0</REB>
          <AST>1</AST>
          <STL>0</STL>
          <BLK>0</BLK>
          <TO>1</TO>
          <PF>2</PF>
          <PTS>5</PTS>
        </player>
      </starters>
      <bench>
        <player>
          <player_name>angok-anyang</player_name>
          <player_jersey>13</player_jersey>
          <pos>F</pos>
          <player_ID>5243157</player_ID>
          <MIN>11</MIN>
          <FGM-A>0-1</FGM-A>
          <_3PM-A>0-1</_3PM-A>
          <FTM-A>0-0</FTM-A>
          <OREB>0</OREB>
          <DREB>2</DREB>
          <REB>2</REB>
          <AST>1</AST>
          <STL>0</STL>
          <BLK>0</BLK>
          <TO>0</TO>
          <PF>1</PF>
          <PTS>0</PTS>
        </player>
        <player>
          <player_name>saliou-seye</player_name>
          <player_jersey>7</player_jersey>
          <pos>F</pos>
          <player_ID>5176661</player_ID>
          <MIN>17</MIN>
          <FGM-A>0-2</FGM-A>
          <_3PM-A>0-1</_3PM-A>
          <FTM-A>0-0</FTM-A>
          <OREB>2</OREB>
          <DREB>3</DREB>
          <REB>5</REB>
          <AST>1</AST>
          <STL>1</STL>
          <BLK>0</BLK>
          <TO>1</TO>
          <PF>3</PF>
          <PTS>0</PTS>
        </player>
        <player>
          <player_name>warren-yeh</player_name>
          <player_jersey>12</player_jersey>
          <pos>G</pos>
          <player_ID>5243156</player_ID>
          <MIN>7</MIN>
          <FGM-A>1-3</FGM-A>
          <_3PM-A>0-1</_3PM-A>
          <FTM-A>0-0</FTM-A>
          <OREB>2</OREB>
          <DREB>1</DREB>
          <REB>3</REB>
          <AST>1</AST>
          <STL>0</STL>
          <BLK>0</BLK>
          <TO>1</TO>
          <PF>3</PF>
          <PTS>2</PTS>
        </player>
        <player>
          <player_name>jaylen-colon</player_name>
          <player_jersey>6</player_jersey>
          <pos>G</pos>
          <player_ID>5243155</player_ID>
          <MIN>18</MIN>
          <FGM-A>3-6</FGM-A>
          <_3PM-A>3-6</_3PM-A>
          <FTM-A>1-2</FTM-A>
          <OREB>1</OREB>
          <DREB>0</DREB>
          <REB>1</REB>
          <AST>2</AST>
          <STL>1</STL>
          <BLK>0</BLK>
          <TO>0</TO>
          <PF>2</PF>
          <PTS>10</PTS>
        </player>
        <player>
          <player_name>aaron-smith</player_name>
          <player_jersey>55</player_jersey>
          <pos>G</pos>
          <player_ID>5177527</player_ID>
          <MIN>8</MIN>
          <FGM-A>0-2</FGM-A>
          <_3PM-A>0-1</_3PM-A>
          <FTM-A>0-0</FTM-A>
          <OREB>0</OREB>
          <DREB>0</DREB>
          <REB>0</REB>
          <AST>0</AST>
          <STL>1</STL>
          <BLK>0</BLK>
          <TO>0</TO>
          <PF>2</PF>
          <PTS>0</PTS>
        </player>
        <player>
          <player_name>dylan-mclean</player_name>
          <player_jersey>8</player_jersey>
          <pos>G</pos>
          <player_ID>5177525</player_ID>
          <MIN>8</MIN>
          <FGM-A>2-4</FGM-A>
          <_3PM-A>1-1</_3PM-A>
          <FTM-A>2-2</FTM-A>
          <OREB>0</OREB>
          <DREB>0</DREB>
          <REB>0</REB>
          <AST>0</AST>
          <STL>0</STL>
          <BLK>0</BLK>
          <TO>0</TO>
          <PF>1</PF>
          <PTS>7</PTS>
        </player>
        <player>
          <player_name>bilal-abdur-rahman</player_name>
          <player_jersey>20</player_jersey>
          <pos>G</pos>
          <player_ID>5177520</player_ID>
          <MIN>14</MIN>
          <FGM-A>1-5</FGM-A>
          <_3PM-A>1-3</_3PM-A>
          <FTM-A>0-0</FTM-A>
          <OREB>0</OREB>
          <DREB>0</DREB>
          <REB>0</REB>
          <AST>2</AST>
          <STL>0</STL>
          <BLK>0</BLK>
          <TO>2</TO>
          <PF>1</PF>
          <PTS>3</PTS>
        </player>
        <player>
          <player_name>darius-ford</player_name>
          <player_jersey>30</player_jersey>
          <pos>G</pos>
          <player_ID>4897751</player_ID>
          <MIN>16</MIN>
          <FGM-A>3-12</FGM-A>
          <_3PM-A>3-8</_3PM-A>
          <FTM-A>2-2</FTM-A>
          <OREB>0</OREB>
          <DREB>0</DREB>
          <REB>0</REB>
          <AST>1</AST>
          <STL>0</STL>
          <BLK>0</BLK>
          <TO>1</TO>
          <PF>2</PF>
          <PTS>11</PTS>
        </player>
      </bench>
      <totals>
        <player>
          <player_name>team</player_name>
          <player_jersey></player_jersey>
          <pos></pos>
          <player_ID>0</player_ID>
          <MIN></MIN>
          <FGM-A>27-65</FGM-A>
          <_3PM-A>11-30</_3PM-A>
          <FTM-A>10-11</FTM-A>
          <OREB>11</OREB>
          <DREB>16</DREB>
          <REB>27</REB>
          <AST>17</AST>
          <STL>7</STL>
          <BLK>6</BLK>
          <TO>11</TO>
          <PF>21</PF>
          <PTS>75</PTS>
        </player>
      </totals>
    </visitor>
    <home>
      <team>Bethune-Cookman Wildcats</team>
      <starters>
        <player>
          <player_name>kalil-camara</player_name>
          <player_jersey>10</player_jersey>
          <pos>F</pos>
          <player_ID>5113823</player_ID>
          <MIN>38</MIN>
          <FGM-A>5-12</FGM-A>
          <_3PM-A>1-6</_3PM-A>
          <FTM-A>4-4</FTM-A>
          <OREB>6</OREB>
          <DREB>2</DREB>
          <REB>8</REB>
          <AST>3</AST>
          <STL>2</STL>
          <BLK>0</BLK>
          <TO>3</TO>
          <PF>0</PF>
          <PTS>15</PTS>
        </player>
        <player>
          <player_name>daniel-rouzan</player_name>
          <player_jersey>23</player_jersey>
          <pos>F</pos>
          <player_ID>5108148</player_ID>
          <MIN>32</MIN>
          <FGM-A>6-12</FGM-A>
          <_3PM-A>0-1</_3PM-A>
          <FTM-A>4-5</FTM-A>
          <OREB>2</OREB>
          <DREB>5</DREB>
          <REB>7</REB>
          <AST>0</AST>
          <STL>0</STL>
          <BLK>2</BLK>
          <TO>3</TO>
          <PF>4</PF>
          <PTS>16</PTS>
        </player>
        <player>
          <player_name>jesus-carralero-martin</player_name>
          <player_jersey>12</player_jersey>
          <pos>F</pos>
          <player_ID>4592654</player_ID>
          <MIN>37</MIN>
          <FGM-A>7-9</FGM-A>
          <_3PM-A>3-4</_3PM-A>
          <FTM-A>0-0</FTM-A>
          <OREB>2</OREB>
          <DREB>9</DREB>
          <REB>11</REB>
          <AST>2</AST>
          <STL>1</STL>
          <BLK>0</BLK>
          <TO>1</TO>
          <PF>2</PF>
          <PTS>17</PTS>
        </player>
        <player>
          <player_name>seneca-willoughby</player_name>
          <player_jersey>3</player_jersey>
          <pos>G</pos>
          <player_ID>5178200</player_ID>
          <MIN>36</MIN>
          <FGM-A>0-1</FGM-A>
          <_3PM-A>0-1</_3PM-A>
          <FTM-A>2-2</FTM-A>
          <OREB>3</OREB>
          <DREB>2</DREB>
          <REB>5</REB>
          <AST>12</AST>
          <STL>2</STL>
          <BLK>0</BLK>
          <TO>1</TO>
          <PF>3</PF>
          <PTS>2</PTS>
        </player>
        <player>
          <player_name>trey-thomas</player_name>
          <player_jersey>1</player_jersey>
          <pos>G</pos>
          <player_ID>5106699</player_ID>
          <MIN>35</MIN>
          <FGM-A>7-21</FGM-A>
          <_3PM-A>1-9</_3PM-A>
          <FTM-A>9-10</FTM-A>
          <OREB>1</OREB>
          <DREB>8</DREB>
          <REB>9</REB>
          <AST>5</AST>
          <STL>2</STL>
          <BLK>0</BLK>
          <TO>4</TO>
          <PF>2</PF>
          <PTS>24</PTS>
        </player>
      </starters>
      <bench>
        <player>
          <player_name>david-onanina</player_name>
          <player_jersey>33</player_jersey>
          <pos>C</pos>
          <player_ID>5106709</player_ID>
          <MIN>15</MIN>
          <FGM-A>6-7</FGM-A>
          <_3PM-A>0-0</_3PM-A>
          <FTM-A>2-3</FTM-A>
          <OREB>0</OREB>
          <DREB>0</DREB>
          <REB>0</REB>
          <AST>1</AST>
          <STL>0</STL>
          <BLK>0</BLK>
          <TO>0</TO>
          <PF>1</PF>
          <PTS>14</PTS>
        </player>
        <player>
          <player_name>trayvon-barbary</player_name>
          <player_jersey>24</player_jersey>
          <pos>G</pos>
          <player_ID>5265246</player_ID>
          <MIN>3</MIN>
          <FGM-A>0-0</FGM-A>
          <_3PM-A>0-0</_3PM-A>
          <FTM-A>0-0</FTM-A>
          <OREB>0</OREB>
          <DREB>0</DREB>
          <REB>0</REB>
          <AST>0</AST>
          <STL>0</STL>
          <BLK>0</BLK>
          <TO>0</TO>
          <PF>0</PF>
          <PTS>0</PTS>
        </player>
        <player>
          <player_name>jarrell-love</player_name>
          <player_jersey>21</player_jersey>
          <pos>G</pos>
          <player_ID>5243202</player_ID>
          <MIN>5</MIN>
          <FGM-A>0-0</FGM-A>
          <_3PM-A>0-0</_3PM-A>
          <FTM-A>1-2</FTM-A>
          <OREB>1</OREB>
          <DREB>0</DREB>
          <REB>1</REB>
          <AST>0</AST>
          <STL>0</STL>
          <BLK>0</BLK>
          <TO>1</TO>
          <PF>1</PF>
          <PTS>1</PTS>
        </player>
      </bench>
      <totals>
        <player>
          <player_name>team</player_name>
          <player_jersey></player_jersey>
          <pos></pos>
          <player_ID>0</player_ID>
          <MIN></MIN>
          <FGM-A>31-62</FGM-A>
          <_3PM-A>5-21</_3PM-A>
          <FTM-A>22-26</FTM-A>
          <OREB>18</OREB>
          <DREB>28</DREB>
          <REB>46</REB>
          <AST>23</AST>
          <STL>7</STL>
          <BLK>2</BLK>
          <TO>13</TO>
          <PF>13</PF>
          <PTS>89</PTS>
        </player>
      </totals>
    </home>
    <flagrant_fouls>None</flagrant_fouls>
    <technicals>
      <person>None</person>
    </technicals>
    <officials>
      <person>None</person>
    </officials>
    <time_of_game></time_of_game>
  </STATS>
  <ESPN_TEAM_ROSTER>
    <visitor>
      <roster_header>Alabama A&amp;M Bulldogs Roster 2024-25</roster_header>
      <coach>Coach Donte' Jackson</coach>
      <player>
        <NO>23</NO>
        <NAME>chad-moodie</NAME>
        <ID>5177526</ID>
        <POS>F</POS>
        <HT></HT>
        <WT></WT>
        <CLASS></CLASS>
        <BIRTHPLACE></BIRTHPLACE>
      </player>
      <player>
        <NO>21</NO>
        <NAME>clance-crosby</NAME>
        <ID>5177522</ID>
        <POS>F</POS>
        <HT></HT>
        <WT></WT>
        <CLASS></CLASS>
        <BIRTHPLACE></BIRTHPLACE>
      </player>
      <player>
        <NO>0</NO>
        <NAME>ac-bryant</NAME>
        <ID>5177521</ID>
        <POS>G</POS>
        <HT></HT>
        <WT></WT>
        <CLASS></CLASS>
        <BIRTHPLACE></BIRTHPLACE>
      </player>
      <player>
        <NO>4</NO>
        <NAME>quincy-mcgriff</NAME>
        <ID>5105886</ID>
        <POS>G</POS>
        <HT></HT>
        <WT></WT>
        <CLASS></CLASS>
        <BIRTHPLACE></BIRTHPLACE>
      </player>
      <player>
        <NO>5</NO>
        <NAME>london-riley</NAME>
        <ID>4703107</ID>
        <POS>G</POS>
        <HT></HT>
        <WT></WT>
        <CLASS></CLASS>
        <BIRTHPLACE></BIRTHPLACE>
      </player>
      <player>
        <NO>13</NO>
        <NAME>angok-anyang</NAME>
        <ID>5243157</ID>
        <POS>F</POS>
        <HT>6-9</HT>
        <WT>215 lbs</WT>
        <CLASS>JR</CLASS>
        <BIRTHPLACE>Adelaide, SA</BIRTHPLACE>
      </player>
      <player>
        <NO>7</NO>
        <NAME>saliou-seye</NAME>
        <ID>5176661</ID>
        <POS>F</POS>
        <HT></HT>
        <WT></WT>
        <CLASS></CLASS>
        <BIRTHPLACE></BIRTHPLACE>
      </player>
      <player>
        <NO>12</NO>
        <NAME>warren-yeh</NAME>
        <ID>5243156</ID>
        <POS>G</POS>
        <HT></HT>
        <WT></WT>
        <CLASS></CLASS>
        <BIRTHPLACE></BIRTHPLACE>
      </player>
      <player>
        <NO>6</NO>
        <NAME>jaylen-colon</NAME>
        <ID>5243155</ID>
        <POS>G</POS>
        <HT></HT>
        <WT></WT>
        <CLASS></CLASS>
        <BIRTHPLACE></BIRTHPLACE>
      </player>
      <player>
        <NO>55</NO>
        <NAME>aaron-smith</NAME>
        <ID>5177527</ID>
        <POS>G</POS>
        <HT></HT>
        <WT></WT>
        <CLASS></CLASS>
        <BIRTHPLACE></BIRTHPLACE>
      </player>
      <player>
        <NO>8</NO>
        <NAME>dylan-mclean</NAME>
        <ID>5177525</ID>
        <POS>G</POS>
        <HT></HT>
        <WT></WT>
        <CLASS></CLASS>
        <BIRTHPLACE></BIRTHPLACE>
      </player>
      <player>
        <NO>2</NO>
        <NAME>bilal-abdur-rahman</NAME>
        <ID>5177520</ID>
        <POS>G</POS>
        <HT>5-11</HT>
        <WT>160 lbs</WT>
        <CLASS>SO</CLASS>
        <BIRTHPLACE>Atlanta, GA</BIRTHPLACE>
      </player>
      <player>
        <NO>30</NO>
        <NAME>darius-ford</NAME>
        <ID>4897751</ID>
        <POS>G</POS>
        <HT></HT>
        <WT></WT>
        <CLASS></CLASS>
        <BIRTHPLACE></BIRTHPLACE>
      </player>
      <player>
        <NO>34</NO>
        <NAME>bol-kuir</NAME>
        <ID>5243158</ID>
        <POS>F</POS>
        <HT></HT>
        <WT></WT>
        <CLASS></CLASS>
        <BIRTHPLACE></BIRTHPLACE>
      </player>
      <player>
        <NO>14</NO>
        <NAME>ademola-oladipo</NAME>
        <ID>5182073</ID>
        <POS>F</POS>
        <HT></HT>
        <WT></WT>
        <CLASS></CLASS>
        <BIRTHPLACE></BIRTHPLACE>
      </player>
      <player>
        <NO>11</NO>
        <NAME>austin-harvell</NAME>
        <ID>4432352</ID>
        <POS>F</POS>
        <HT></HT>
        <WT></WT>
        <CLASS></CLASS>
        <BIRTHPLACE></BIRTHPLACE>
      </player>
      <player>
        <NO>24</NO>
        <NAME>nari-jordan</NAME>
        <ID>5177524</ID>
        <POS>G</POS>
        <HT></HT>
        <WT></WT>
        <CLASS></CLASS>
        <BIRTHPLACE></BIRTHPLACE>
      </player>
      <player>
        <NO>1</NO>
        <NAME>joshua-hughley</NAME>
        <ID>5177523</ID>
        <POS>G</POS>
        <HT></HT>
        <WT></WT>
        <CLASS></CLASS>
        <BIRTHPLACE></BIRTHPLACE>
      </player>
      <player>
        <NO>9</NO>
        <NAME>ejay-greer</NAME>
        <ID>5176154</ID>
        <POS>G</POS>
        <HT></HT>
        <WT></WT>
        <CLASS></CLASS>
        <BIRTHPLACE></BIRTHPLACE>
      </player>
      <player>
        <NO>22</NO>
        <NAME>lorenzo-downey</NAME>
        <ID>5107456</ID>
        <POS>G</POS>
        <HT></HT>
        <WT></WT>
        <CLASS></CLASS>
        <BIRTHPLACE></BIRTHPLACE>
      </player>
      <player>
        <NO>24</NO>
        <NAME>eric-lee</NAME>
        <ID>4703109</ID>
        <POS>G</POS>
        <HT></HT>
        <WT></WT>
        <CLASS></CLASS>
        <BIRTHPLACE></BIRTHPLACE>
      </player>
    </visitor>
    <home>
      <roster_header>Bethune-Cookman Wildcats Roster 2024-25</roster_header>
      <coach>Coach Reggie Theus</coach>
      <player>
        <NO>10</NO>
        <NAME>kalil-camara</NAME>
        <ID>5113823</ID>
        <POS>F</POS>
        <HT></HT>
        <WT></WT>
        <CLASS></CLASS>
        <BIRTHPLACE></BIRTHPLACE>
      </player>
      <player>
        <NO>23</NO>
        <NAME>daniel-rouzan</NAME>
        <ID>5108148</ID>
        <POS>F</POS>
        <HT>6-8</HT>
        <WT>235 lbs</WT>
        <CLASS>SR</CLASS>
        <BIRTHPLACE>Las Vegas, NV</BIRTHPLACE>
      </player>
      <player>
        <NO>12</NO>
        <NAME>jesus-carralero-martin</NAME>
        <ID>4592654</ID>
        <POS>F</POS>
        <HT></HT>
        <WT></WT>
        <CLASS></CLASS>
        <BIRTHPLACE></BIRTHPLACE>
      </player>
      <player>
        <NO>3</NO>
        <NAME>seneca-willoughby</NAME>
        <ID>5178200</ID>
        <POS>G</POS>
        <HT>6-3</HT>
        <WT>185 lbs</WT>
        <CLASS>SR</CLASS>
        <BIRTHPLACE>Philadelphia, PA</BIRTHPLACE>
      </player>
      <player>
        <NO>1</NO>
        <NAME>trey-thomas</NAME>
        <ID>5106699</ID>
        <POS>G</POS>
        <HT></HT>
        <WT></WT>
        <CLASS></CLASS>
        <BIRTHPLACE></BIRTHPLACE>
      </player>
      <player>
        <NO>33</NO>
        <NAME>david-onanina</NAME>
        <ID>5106709</ID>
        <POS>C</POS>
        <HT>6-8</HT>
        <WT>230 lbs</WT>
        <CLASS>JR</CLASS>
        <BIRTHPLACE>Yaounde</BIRTHPLACE>
      </player>
      <player>
        <NO>24</NO>
        <NAME>trayvon-barbary</NAME>
        <ID>5265246</ID>
        <POS>G</POS>
        <HT>6-4</HT>
        <WT>175 lbs</WT>
        <CLASS>SR</CLASS>
        <BIRTHPLACE>DeLand, FL</BIRTHPLACE>
      </player>
      <player>
        <NO>21</NO>
        <NAME>jarrell-love</NAME>
        <ID>5243202</ID>
        <POS>G</POS>
        <HT></HT>
        <WT></WT>
        <CLASS></CLASS>
        <BIRTHPLACE></BIRTHPLACE>
      </player>
      <player>
        <NO>15</NO>
        <NAME>reggie-ward-jr</NAME>
        <ID>5178203</ID>
        <POS>F</POS>
        <HT>6-6</HT>
        <WT>230 lbs</WT>
        <CLASS>SR</CLASS>
        <BIRTHPLACE>Chicago, IL</BIRTHPLACE>
      </player>
      <player>
        <NO>32</NO>
        <NAME>jerome-beya</NAME>
        <ID>5107615</ID>
        <POS>F</POS>
        <HT></HT>
        <WT></WT>
        <CLASS></CLASS>
        <BIRTHPLACE></BIRTHPLACE>
      </player>
      <player>
        <NO>22</NO>
        <NAME>william-gonzalez</NAME>
        <ID>5243201</ID>
        <POS>G</POS>
        <HT>6-6</HT>
        <WT>180 lbs</WT>
        <CLASS>FR</CLASS>
        <BIRTHPLACE>Chicago, IL</BIRTHPLACE>
      </player>
      <player>
        <NO>11</NO>
        <NAME>mason-dorsey</NAME>
        <ID>5178202</ID>
        <POS>G</POS>
        <HT></HT>
        <WT></WT>
        <CLASS></CLASS>
        <BIRTHPLACE></BIRTHPLACE>
      </player>
      <player>
        <NO>30</NO>
        <NAME>simeon-womack</NAME>
        <ID>5108848</ID>
        <POS>G</POS>
        <HT>6-2</HT>
        <WT>170 lbs</WT>
        <CLASS>SR</CLASS>
        <BIRTHPLACE>Jacksonville, FL</BIRTHPLACE>
      </player>
      <player>
        <NO>2</NO>
        <NAME>brayon-freeman</NAME>
        <ID>4613126</ID>
        <POS>G</POS>
        <HT></HT>
        <WT></WT>
        <CLASS></CLASS>
        <BIRTHPLACE></BIRTHPLACE>
      </player>
      <player>
        <NO>5</NO>
        <NAME>gianni-hunt</NAME>
        <ID>4431815</ID>
        <POS>G</POS>
        <HT></HT>
        <WT></WT>
        <CLASS></CLASS>
        <BIRTHPLACE></BIRTHPLACE>
      </player>
      <player>
        <NO>4</NO>
        <NAME>antwann-jones</NAME>
        <ID>4396634</ID>
        <POS>G</POS>
        <HT></HT>
        <WT></WT>
        <CLASS></CLASS>
        <BIRTHPLACE></BIRTHPLACE>
      </player>
    </home>
  </ESPN_TEAM_ROSTER>
  <ESPN_RECAP></ESPN_RECAP>
  <ESPN_PLAYBYPLAY></ESPN_PLAYBYPLAY>
</ESPN_EVENT>