<?xml version="1.0" encoding="UTF-8" standalone="no"?>
<ESPN_EVENT>
  <gameID>401625681</gameID>
  <visitor>Maryland Terrapins</visitor>
  <home>Wisconsin Badgers</home>
  <date>20240314</date>
  <ESPN_DATA_PARSE_VERSION>20240314</ESPN_DATA_PARSE_VERSION>
  <ESPN_BOX_URL>https://www.espn.com/mens-college-basketball/game/_/gameId/401625681/maryland-wisconsin</ESPN_BOX_URL>
  <RESULT>
    <visitor>
      <id>120</id>
      <team_long>Maryland Terrapins</team_long>
      <team_short>Md</team_short>
      <T>56</T>
      <score>(0-0)</score>
    </visitor>
    <home>
      <id>275</id>
      <team_long>Wisconsin Badgers</team_long>
      <team_short>Wis</team_short>
      <T>87</T>
      <score>(0-0)</score>
    </home>
  </RESULT>
  <GAME_TIME_AND_LOCATION>
    <date>20240314</date>
    <unix_time>1710374400</unix_time>
    <location>Target Center, Minneapolis, MN</location>
    <attendance>Attendance: 0</attendance>
    <capacity></capacity>
  </GAME_TIME_AND_LOCATION>
  <LINESCORE>
    <visitor>
      <id></id>
      <team_long>Maryland Terrapins</team_long>
      <c1>26</c1>
      <c2>30</c2>
      <T>56</T>
    </visitor>
    <home>
      <id></id>
      <team_long>Wisconsin Badgers</team_long>
      <c1>47</c1>
      <c2>40</c2>
      <T>87</T>
    </home>
  </LINESCORE>
  <GAME_NOTES>
    <top_performers>
      <assists>
        <home>
          <player>
            <player_name>chucky-hepburn</player_name>
            <player_ID>4590360</player_ID>
            <ast>8</ast>
            <to>2</to>
            <min>21</min>
          </player>
        </home>
        <visitor>
          <player>
            <player_name>deshawn-harris-smith</player_name>
            <player_ID>4848622</player_ID>
            <ast>3</ast>
            <to>1</to>
            <min>32</min>
          </player>
        </visitor>
      </assists>
      <points>
        <home>
          <player>
            <player_name>john-blackwell</player_name>
            <player_ID>5103630</player_ID>
            <pts>18</pts>
            <fg>6/11</fg>
            <ft>2/2</ft>
          </player>
        </home>
        <visitor>
          <player>
            <player_name>jahmir-young</player_name>
            <player_ID>4433133</player_ID>
            <pts>18</pts>
            <fg>8/15</fg>
            <ft>0/1</ft>
          </player>
        </visitor>
      </points>
      <rebounds>
        <home>
          <player>
            <player_name>john-blackwell</player_name>
            <player_ID>5103630</player_ID>
            <reb>5</reb>
            <dreb>4</dreb>
            <oreb>1</oreb>
          </player>
        </home>
        <visitor>
          <player>
            <player_name>julian-reese</player_name>
            <player_ID>4683742</player_ID>
            <reb>5</reb>
            <dreb>5</dreb>
            <oreb>0</oreb>
          </player>
        </visitor>
      </rebounds>
    </top_performers>
  </GAME_NOTES>
  <STATS>
    <visitor>
      <team>Maryland Terrapins</team>
      <starters>
        <player>
          <player_name>julian-reese</player_name>
          <player_jersey>10</player_jersey>
          <pos>F</pos>
          <player_ID>4683742</player_ID>
          <MIN>30</MIN>
          <FGM-A>4-8</FGM-A>
          <_3PM-A>0-0</_3PM-A>
          <FTM-A>2-2</FTM-A>
          <OREB>0</OREB>
          <DREB>5</DREB>
          <REB>5</REB>
          <AST>2</AST>
          <STL>0</STL>
          <BLK>2</BLK>
          <TO>3</TO>
          <PF>1</PF>
          <PTS>10</PTS>
        </player>
        <player>
          <player_name>donta-scott</player_name>
          <player_jersey>24</player_jersey>
          <pos>F</pos>
          <player_ID>4432852</player_ID>
          <MIN>25</MIN>
          <FGM-A>1-4</FGM-A>
          <_3PM-A>0-1</_3PM-A>
          <FTM-A>2-2</FTM-A>
          <OREB>2</OREB>
          <DREB>0</DREB>
          <REB>2</REB>
          <AST>1</AST>
          <STL>1</STL>
          <BLK>0</BLK>
          <TO>4</TO>
          <PF>1</PF>
          <PTS>4</PTS>
        </player>
        <player>
          <player_name>jamie-kaiser-jr</player_name>
          <player_jersey>12</player_jersey>
          <pos>G</pos>
          <player_ID>5060688</player_ID>
          <MIN>18</MIN>
          <FGM-A>1-6</FGM-A>
          <_3PM-A>1-3</_3PM-A>
          <FTM-A>0-0</FTM-A>
          <OREB>0</OREB>
          <DREB>0</DREB>
          <REB>0</REB>
          <AST>0</AST>
          <STL>0</STL>
          <BLK>0</BLK>
          <TO>1</TO>
          <PF>2</PF>
          <PTS>3</PTS>
        </player>
        <player>
          <player_name>deshawn-harris-smith</player_name>
          <player_jersey>5</player_jersey>
          <pos>G</pos>
          <player_ID>4848622</player_ID>
          <MIN>32</MIN>
          <FGM-A>6-15</FGM-A>
          <_3PM-A>3-4</_3PM-A>
          <FTM-A>1-3</FTM-A>
          <OREB>1</OREB>
          <DREB>1</DREB>
          <REB>2</REB>
          <AST>3</AST>
          <STL>0</STL>
          <BLK>0</BLK>
          <TO>1</TO>
          <PF>2</PF>
          <PTS>16</PTS>
        </player>
        <player>
          <player_name>jahmir-young</player_name>
          <player_jersey>1</player_jersey>
          <pos>G</pos>
          <player_ID>4433133</player_ID>
          <MIN>30</MIN>
          <FGM-A>8-15</FGM-A>
          <_3PM-A>2-5</_3PM-A>
          <FTM-A>0-1</FTM-A>
          <OREB>0</OREB>
          <DREB>1</DREB>
          <REB>1</REB>
          <AST>2</AST>
          <STL>3</STL>
          <BLK>1</BLK>
          <TO>2</TO>
          <PF>1</PF>
          <PTS>18</PTS>
        </player>
      </starters>
      <bench>
        <player>
          <player_name>caelum-swanton-rodger</player_name>
          <player_jersey>35</player_jersey>
          <pos>F</pos>
          <player_ID>5105804</player_ID>
          <MIN>8</MIN>
          <FGM-A>0-1</FGM-A>
          <_3PM-A>0-0</_3PM-A>
          <FTM-A>0-0</FTM-A>
          <OREB>1</OREB>
          <DREB>0</DREB>
          <REB>1</REB>
          <AST>0</AST>
          <STL>0</STL>
          <BLK>1</BLK>
          <TO>0</TO>
          <PF>0</PF>
          <PTS>0</PTS>
        </player>
        <player>
          <player_name>jordan-geronimo</player_name>
          <player_jersey>22</player_jersey>
          <pos>F</pos>
          <player_ID>4432512</player_ID>
          <MIN>22</MIN>
          <FGM-A>1-4</FGM-A>
          <_3PM-A>0-1</_3PM-A>
          <FTM-A>1-2</FTM-A>
          <OREB>1</OREB>
          <DREB>3</DREB>
          <REB>4</REB>
          <AST>1</AST>
          <STL>2</STL>
          <BLK>0</BLK>
          <TO>0</TO>
          <PF>3</PF>
          <PTS>3</PTS>
        </player>
        <player>
          <player_name>noah-batchelor</player_name>
          <player_jersey>11</player_jersey>
          <pos>G</pos>
          <player_ID>5105803</player_ID>
          <MIN>23</MIN>
          <FGM-A>1-2</FGM-A>
          <_3PM-A>0-1</_3PM-A>
          <FTM-A>0-0</FTM-A>
          <OREB>0</OREB>
          <DREB>3</DREB>
          <REB>3</REB>
          <AST>1</AST>
          <STL>1</STL>
          <BLK>0</BLK>
          <TO>0</TO>
          <PF>1</PF>
          <PTS>2</PTS>
        </player>
        <player>
          <player_name>jahnathan-lamothe</player_name>
          <player_jersey>0</player_jersey>
          <pos>G</pos>
          <player_ID>4711264</player_ID>
          <MIN>12</MIN>
          <FGM-A>0-1</FGM-A>
          <_3PM-A>0-0</_3PM-A>
          <FTM-A>0-0</FTM-A>
          <OREB>1</OREB>
          <DREB>0</DREB>
          <REB>1</REB>
          <AST>0</AST>
          <STL>0</STL>
          <BLK>0</BLK>
          <TO>0</TO>
          <PF>0</PF>
          <PTS>0</PTS>
        </player>
      </bench>
      <totals>
        <player>
          <player_name>team</player_name>
          <player_jersey></player_jersey>
          <pos></pos>
          <player_ID>0</player_ID>
          <MIN></MIN>
          <FGM-A>22-56</FGM-A>
          <_3PM-A>6-15</_3PM-A>
          <FTM-A>6-10</FTM-A>
          <OREB>7</OREB>
          <DREB>18</DREB>
          <REB>25</REB>
          <AST>10</AST>
          <STL>7</STL>
          <BLK>4</BLK>
          <TO>11</TO>
          <PF>11</PF>
          <PTS>56</PTS>
        </player>
      </totals>
    </visitor>
    <home>
      <team>Wisconsin Badgers</team>
      <starters>
        <player>
          <player_name>steven-crowl</player_name>
          <player_jersey>22</player_jersey>
          <pos>F</pos>
          <player_ID>4588201</player_ID>
          <MIN>18</MIN>
          <FGM-A>7-8</FGM-A>
          <_3PM-A>3-3</_3PM-A>
          <FTM-A>0-0</FTM-A>
          <OREB>2</OREB>
          <DREB>1</DREB>
          <REB>3</REB>
          <AST>2</AST>
          <STL>0</STL>
          <BLK>0</BLK>
          <TO>2</TO>
          <PF>2</PF>
          <PTS>17</PTS>
        </player>
        <player>
          <player_name>tyler-wahl</player_name>
          <player_jersey>5</player_jersey>
          <pos>F</pos>
          <player_ID>4433105</player_ID>
          <MIN>22</MIN>
          <FGM-A>1-5</FGM-A>
          <_3PM-A>0-1</_3PM-A>
          <FTM-A>2-2</FTM-A>
          <OREB>0</OREB>
          <DREB>0</DREB>
          <REB>0</REB>
          <AST>2</AST>
          <STL>3</STL>
          <BLK>0</BLK>
          <TO>1</TO>
          <PF>1</PF>
          <PTS>4</PTS>
        </player>
        <player>
          <player_name>aj-storr</player_name>
          <player_jersey>2</player_jersey>
          <pos>G</pos>
          <player_ID>5105603</player_ID>
          <MIN>22</MIN>
          <FGM-A>6-11</FGM-A>
          <_3PM-A>2-4</_3PM-A>
          <FTM-A>2-2</FTM-A>
          <OREB>1</OREB>
          <DREB>4</DREB>
          <REB>5</REB>
          <AST>0</AST>
          <STL>1</STL>
          <BLK>0</BLK>
          <TO>2</TO>
          <PF>1</PF>
          <PTS>16</PTS>
        </player>
        <player>
          <player_name>max-klesmit</player_name>
          <player_jersey>11</player_jersey>
          <pos>G</pos>
          <player_ID>4703885</player_ID>
          <MIN>23</MIN>
          <FGM-A>1-2</FGM-A>
          <_3PM-A>1-2</_3PM-A>
          <FTM-A>0-0</FTM-A>
          <OREB>0</OREB>
          <DREB>3</DREB>
          <REB>3</REB>
          <AST>5</AST>
          <STL>0</STL>
          <BLK>0</BLK>
          <TO>0</TO>
          <PF>3</PF>
          <PTS>3</PTS>
        </player>
        <player>
          <player_name>chucky-hepburn</player_name>
          <player_jersey>23</player_jersey>
          <pos>G</pos>
          <player_ID>4590360</player_ID>
          <MIN>21</MIN>
          <FGM-A>4-4</FGM-A>
          <_3PM-A>2-2</_3PM-A>
          <FTM-A>0-0</FTM-A>
          <OREB>0</OREB>
          <DREB>3</DREB>
          <REB>3</REB>
          <AST>8</AST>
          <STL>0</STL>
          <BLK>1</BLK>
          <TO>2</TO>
          <PF>1</PF>
          <PTS>10</PTS>
        </player>
      </starters>
      <bench>
        <player>
          <player_name>nolan-winter</player_name>
          <player_jersey>31</player_jersey>
          <pos>F</pos>
          <player_ID>4895783</player_ID>
          <MIN>15</MIN>
          <FGM-A>2-5</FGM-A>
          <_3PM-A>1-1</_3PM-A>
          <FTM-A>1-2</FTM-A>
          <OREB>0</OREB>
          <DREB>5</DREB>
          <REB>5</REB>
          <AST>2</AST>
          <STL>0</STL>
          <BLK>0</BLK>
          <TO>1</TO>
          <PF>0</PF>
          <PTS>6</PTS>
        </player>
        <player>
          <player_name>markus-ilver</player_name>
          <player_jersey>35</player_jersey>
          <pos>F</pos>
          <player_ID>4715351</player_ID>
          <MIN>15</MIN>
          <FGM-A>0-2</FGM-A>
          <_3PM-A>0-1</_3PM-A>
          <FTM-A>0-0</FTM-A>
          <OREB>0</OREB>
          <DREB>2</DREB>
          <REB>2</REB>
          <AST>1</AST>
          <STL>0</STL>
          <BLK>0</BLK>
          <TO>0</TO>
          <PF>3</PF>
          <PTS>0</PTS>
        </player>
        <player>
          <player_name>carter-gilmore</player_name>
          <player_jersey>14</player_jersey>
          <pos>F</pos>
          <player_ID>4702534</player_ID>
          <MIN>11</MIN>
          <FGM-A>1-4</FGM-A>
          <_3PM-A>1-1</_3PM-A>
          <FTM-A>0-0</FTM-A>
          <OREB>2</OREB>
          <DREB>1</DREB>
          <REB>3</REB>
          <AST>3</AST>
          <STL>0</STL>
          <BLK>0</BLK>
          <TO>2</TO>
          <PF>2</PF>
          <PTS>3</PTS>
        </player>
        <player>
          <player_name>chris-hodges</player_name>
          <player_jersey>21</player_jersey>
          <pos>F</pos>
          <player_ID>4433615</player_ID>
          <MIN>5</MIN>
          <FGM-A>0-3</FGM-A>
          <_3PM-A>0-0</_3PM-A>
          <FTM-A>1-2</FTM-A>
          <OREB>3</OREB>
          <DREB>1</DREB>
          <REB>4</REB>
          <AST>1</AST>
          <STL>0</STL>
          <BLK>1</BLK>
          <TO>0</TO>
          <PF>0</PF>
          <PTS>1</PTS>
        </player>
        <player>
          <player_name>luke-haertle</player_name>
          <player_jersey>12</player_jersey>
          <pos>G</pos>
          <player_ID>5105862</player_ID>
          <MIN>3</MIN>
          <FGM-A>0-0</FGM-A>
          <_3PM-A>0-0</_3PM-A>
          <FTM-A>0-0</FTM-A>
          <OREB>0</OREB>
          <DREB>0</DREB>
          <REB>0</REB>
          <AST>0</AST>
          <STL>0</STL>
          <BLK>0</BLK>
          <TO>1</TO>
          <PF>0</PF>
          <PTS>0</PTS>
        </player>
        <player>
          <player_name>connor-essegian</player_name>
          <player_jersey>3</player_jersey>
          <pos>G</pos>
          <player_ID>5105861</player_ID>
          <MIN>9</MIN>
          <FGM-A>3-5</FGM-A>
          <_3PM-A>2-4</_3PM-A>
          <FTM-A>1-1</FTM-A>
          <OREB>0</OREB>
          <DREB>1</DREB>
          <REB>1</REB>
          <AST>0</AST>
          <STL>0</STL>
          <BLK>0</BLK>
          <TO>0</TO>
          <PF>0</PF>
          <PTS>9</PTS>
        </player>
        <player>
          <player_name>john-blackwell</player_name>
          <player_jersey>25</player_jersey>
          <pos>G</pos>
          <player_ID>5103630</player_ID>
          <MIN>23</MIN>
          <FGM-A>6-11</FGM-A>
          <_3PM-A>4-6</_3PM-A>
          <FTM-A>2-2</FTM-A>
          <OREB>1</OREB>
          <DREB>4</DREB>
          <REB>5</REB>
          <AST>0</AST>
          <STL>0</STL>
          <BLK>0</BLK>
          <TO>0</TO>
          <PF>1</PF>
          <PTS>18</PTS>
        </player>
        <player>
          <player_name>kamari-mcgee</player_name>
          <player_jersey>4</player_jersey>
          <pos>G</pos>
          <player_ID>4897723</player_ID>
          <MIN>13</MIN>
          <FGM-A>0-0</FGM-A>
          <_3PM-A>0-0</_3PM-A>
          <FTM-A>0-0</FTM-A>
          <OREB>0</OREB>
          <DREB>1</DREB>
          <REB>1</REB>
          <AST>1</AST>
          <STL>1</STL>
          <BLK>0</BLK>
          <TO>1</TO>
          <PF>3</PF>
          <PTS>0</PTS>
        </player>
      </bench>
      <totals>
        <player>
          <player_name>team</player_name>
          <player_jersey></player_jersey>
          <pos></pos>
          <player_ID>0</player_ID>
          <MIN></MIN>
          <FGM-A>31-60</FGM-A>
          <_3PM-A>16-25</_3PM-A>
          <FTM-A>9-11</FTM-A>
          <OREB>12</OREB>
          <DREB>30</DREB>
          <REB>42</REB>
          <AST>25</AST>
          <STL>5</STL>
          <BLK>2</BLK>
          <TO>13</TO>
          <PF>17</PF>
          <PTS>87</PTS>
        </player>
      </totals>
    </home>
    <flagrant_fouls>None</flagrant_fouls>
    <technicals>
      <person>None</person>
    </technicals>
    <officials>
      <person>None</person>
    </officials>
    <time_of_game></time_of_game>
  </STATS>
  <ESPN_TEAM_ROSTER>
    <visitor>
      <roster_header>Maryland Terrapins Roster 2023-24</roster_header>
      <coach>Coach Buzz Williams</coach>
      <player>
        <NO>10</NO>
        <NAME>julian-reese</NAME>
        <ID>4683742</ID>
        <POS>F</POS>
        <HT></HT>
        <WT></WT>
        <CLASS></CLASS>
        <BIRTHPLACE></BIRTHPLACE>
      </player>
      <player>
        <NO>24</NO>
        <NAME>donta-scott</NAME>
        <ID>4432852</ID>
        <POS>F</POS>
        <HT></HT>
        <WT></WT>
        <CLASS></CLASS>
        <BIRTHPLACE></BIRTHPLACE>
      </player>
      <player>
        <NO>12</NO>
        <NAME>jamie-kaiser-jr</NAME>
        <ID>5060688</ID>
        <POS>G</POS>
        <HT></HT>
        <WT></WT>
        <CLASS></CLASS>
        <BIRTHPLACE></BIRTHPLACE>
      </player>
      <player>
        <NO>5</NO>
        <NAME>deshawn-harris-smith</NAME>
        <ID>4848622</ID>
        <POS>G</POS>
        <HT></HT>
        <WT></WT>
        <CLASS></CLASS>
        <BIRTHPLACE></BIRTHPLACE>
      </player>
      <player>
        <NO>1</NO>
        <NAME>jahmir-young</NAME>
        <ID>4433133</ID>
        <POS>G</POS>
        <HT></HT>
        <WT></WT>
        <CLASS></CLASS>
        <BIRTHPLACE></BIRTHPLACE>
      </player>
      <player>
        <NO>35</NO>
        <NAME>caelum-swanton-rodger</NAME>
        <ID>5105804</ID>
        <POS>F</POS>
        <HT></HT>
        <WT></WT>
        <CLASS></CLASS>
        <BIRTHPLACE></BIRTHPLACE>
      </player>
      <player>
        <NO>22</NO>
        <NAME>jordan-geronimo</NAME>
        <ID>4432512</ID>
        <POS>F</POS>
        <HT></HT>
        <WT></WT>
        <CLASS></CLASS>
        <BIRTHPLACE></BIRTHPLACE>
      </player>
      <player>
        <NO>11</NO>
        <NAME>noah-batchelor</NAME>
        <ID>5105803</ID>
        <POS>G</POS>
        <HT></HT>
        <WT></WT>
        <CLASS></CLASS>
        <BIRTHPLACE></BIRTHPLACE>
      </player>
      <player>
        <NO>0</NO>
        <NAME>jahnathan-lamothe</NAME>
        <ID>4711264</ID>
        <POS>G</POS>
        <HT></HT>
        <WT></WT>
        <CLASS></CLASS>
        <BIRTHPLACE></BIRTHPLACE>
      </player>
      <player>
        <NO>14</NO>
        <NAME>mady-traore</NAME>
        <ID>5122917</ID>
        <POS>F</POS>
        <HT></HT>
        <WT></WT>
        <CLASS></CLASS>
        <BIRTHPLACE></BIRTHPLACE>
      </player>
      <player>
        <NO>4</NO>
        <NAME>braden-pierce</NAME>
        <ID>5142360</ID>
        <POS>C</POS>
        <HT></HT>
        <WT></WT>
        <CLASS></CLASS>
        <BIRTHPLACE></BIRTHPLACE>
      </player>
      <player>
        <NO>30</NO>
        <NAME>lukas-sotell</NAME>
        <ID>5181259</ID>
        <POS>G</POS>
        <HT>6-3</HT>
        <WT>180 lbs</WT>
        <CLASS>JR</CLASS>
        <BIRTHPLACE>Stamford, CT</BIRTHPLACE>
      </player>
      <player>
        <NO>40</NO>
        <NAME>ben-murphy</NAME>
        <ID>5181258</ID>
        <POS>G</POS>
        <HT></HT>
        <WT></WT>
        <CLASS></CLASS>
        <BIRTHPLACE></BIRTHPLACE>
      </player>
      <player>
        <NO>13</NO>
        <NAME>chance-stephens</NAME>
        <ID>5105459</ID>
        <POS>G</POS>
        <HT></HT>
        <WT></WT>
        <CLASS></CLASS>
        <BIRTHPLACE></BIRTHPLACE>
      </player>
      <player>
        <NO>2</NO>
        <NAME>jahari-long</NAME>
        <ID>4433512</ID>
        <POS>G</POS>
        <HT></HT>
        <WT></WT>
        <CLASS></CLASS>
        <BIRTHPLACE></BIRTHPLACE>
      </player>
    </visitor>
    <home>
      <roster_header>Wisconsin Badgers Roster 2023-24</roster_header>
      <coach>Coach Greg Gard</coach>
      <player>
        <NO>22</NO>
        <NAME>steven-crowl</NAME>
        <ID>4588201</ID>
        <POS>F</POS>
        <HT></HT>
        <WT></WT>
        <CLASS></CLASS>
        <BIRTHPLACE></BIRTHPLACE>
      </player>
      <player>
        <NO>5</NO>
        <NAME>tyler-wahl</NAME>
        <ID>4433105</ID>
        <POS>F</POS>
        <HT></HT>
        <WT></WT>
        <CLASS></CLASS>
        <BIRTHPLACE></BIRTHPLACE>
      </player>
      <player>
        <NO>2</NO>
        <NAME>aj-storr</NAME>
        <ID>5105603</ID>
        <POS>G</POS>
        <HT></HT>
        <WT></WT>
        <CLASS></CLASS>
        <BIRTHPLACE></BIRTHPLACE>
      </player>
      <player>
        <NO>11</NO>
        <NAME>max-klesmit</NAME>
        <ID>4703885</ID>
        <POS>G</POS>
        <HT></HT>
        <WT></WT>
        <CLASS></CLASS>
        <BIRTHPLACE></BIRTHPLACE>
      </player>
      <player>
        <NO>23</NO>
        <NAME>chucky-hepburn</NAME>
        <ID>4590360</ID>
        <POS>G</POS>
        <HT></HT>
        <WT></WT>
        <CLASS></CLASS>
        <BIRTHPLACE></BIRTHPLACE>
      </player>
      <player>
        <NO>31</NO>
        <NAME>nolan-winter</NAME>
        <ID>4895783</ID>
        <POS>F</POS>
        <HT>7-0</HT>
        <WT>235 lbs</WT>
        <CLASS>JR</CLASS>
        <BIRTHPLACE>Lakeville, MN</BIRTHPLACE>
      </player>
      <player>
        <NO>35</NO>
        <NAME>markus-ilver</NAME>
        <ID>4715351</ID>
        <POS>F</POS>
        <HT></HT>
        <WT></WT>
        <CLASS></CLASS>
        <BIRTHPLACE></BIRTHPLACE>
      </player>
      <player>
        <NO>14</NO>
        <NAME>carter-gilmore</NAME>
        <ID>4702534</ID>
        <POS>F</POS>
        <HT></HT>
        <WT></WT>
        <CLASS></CLASS>
        <BIRTHPLACE></BIRTHPLACE>
      </player>
      <player>
        <NO>21</NO>
        <NAME>chris-hodges</NAME>
        <ID>4433615</ID>
        <POS>F</POS>
        <HT></HT>
        <WT></WT>
        <CLASS></CLASS>
        <BIRTHPLACE></BIRTHPLACE>
      </player>
      <player>
        <NO>12</NO>
        <NAME>luke-haertle</NAME>
        <ID>5105862</ID>
        <POS>G</POS>
        <HT></HT>
        <WT></WT>
        <CLASS></CLASS>
        <BIRTHPLACE></BIRTHPLACE>
      </player>
      <player>
        <NO>3</NO>
        <NAME>connor-essegian</NAME>
        <ID>5105861</ID>
        <POS>G</POS>
        <HT></HT>
        <WT></WT>
        <CLASS></CLASS>
        <BIRTHPLACE></BIRTHPLACE>
      </player>
      <player>
        <NO>25</NO>
        <NAME>john-blackwell</NAME>
        <ID>5103630</ID>
        <POS>G</POS>
        <HT>6-4</HT>
        <WT>203 lbs</WT>
        <CLASS>JR</CLASS>
        <BIRTHPLACE>Bloomfield Hills, MI</BIRTHPLACE>
      </player>
      <player>
        <NO>4</NO>
        <NAME>kamari-mcgee</NAME>
        <ID>4897723</ID>
        <POS>G</POS>
        <HT></HT>
        <WT></WT>
        <CLASS></CLASS>
        <BIRTHPLACE></BIRTHPLACE>
      </player>
      <player>
        <NO>34</NO>
        <NAME>gus-yalden</NAME>
        <ID>4685686</ID>
        <POS>F</POS>
        <HT></HT>
        <WT></WT>
        <CLASS></CLASS>
        <BIRTHPLACE></BIRTHPLACE>
      </player>
      <player>
        <NO>5</NO>
        <NAME>jack-janicki</NAME>
        <ID>5174807</ID>
        <POS>G</POS>
        <HT>6-5</HT>
        <WT>200 lbs</WT>
        <CLASS>SO</CLASS>
        <BIRTHPLACE>White Bear Lake, MN</BIRTHPLACE>
      </player>
      <player>
        <NO>30</NO>
        <NAME>ross-candelino</NAME>
        <ID>5105864</ID>
        <POS>G</POS>
        <HT></HT>
        <WT></WT>
        <CLASS></CLASS>
        <BIRTHPLACE></BIRTHPLACE>
      </player>
      <player>
        <NO>15</NO>
        <NAME>isaac-gard</NAME>
        <ID>5105863</ID>
        <POS>G</POS>
        <HT>6-3</HT>
        <WT>170 lbs</WT>
        <CLASS>SR</CLASS>
        <BIRTHPLACE>Oregon, WI</BIRTHPLACE>
      </player>
      <player>
        <NO>10</NO>
        <NAME>isaac-lindsey</NAME>
        <ID>4703389</ID>
        <POS>G</POS>
        <HT></HT>
        <WT></WT>
        <CLASS></CLASS>
        <BIRTHPLACE></BIRTHPLACE>
      </player>
    </home>
  </ESPN_TEAM_ROSTER>
  <ESPN_RECAP>Crowl, Blackwell make 7 of Wisconsin's season-high 16 3s in 87-56 win over Maryland in Big Ten</ESPN_RECAP>
  <ESPN_PLAYBYPLAY></ESPN_PLAYBYPLAY>
</ESPN_EVENT>