<?xml version="1.0" encoding="UTF-8" standalone="no"?>
<ESPN_EVENT>
  <gameID>401577681</gameID>
  <visitor>Coast Guard Bears</visitor>
  <home>Quinnipiac Bobcats</home>
  <date>20231106</date>
  <ESPN_DATA_PARSE_VERSION>20231106</ESPN_DATA_PARSE_VERSION>
  <ESPN_BOX_URL>https://www.espn.com/mens-college-basketball/game/_/gameId/401577681/coast-guard-quinnipiac</ESPN_BOX_URL>
  <RESULT>
    <visitor>
      <id>2557</id>
      <team_long>Coast Guard Bears</team_long>
      <team_short>Uscg</team_short>
      <T>48</T>
      <score>(0-0)</score>
    </visitor>
    <home>
      <id>2514</id>
      <team_long>Quinnipiac Bobcats</team_long>
      <team_short>Quin</team_short>
      <T>116</T>
      <score>(0-0)</score>
    </home>
  </RESULT>
  <GAME_TIME_AND_LOCATION>
    <date>20231106</date>
    <unix_time>1699315200</unix_time>
    <location>M&amp;T Bank Arena, Hamden, CT</location>
    <attendance>Attendance: 898</attendance>
    <capacity></capacity>
  </GAME_TIME_AND_LOCATION>
  <LINESCORE>
    <visitor>
      <id></id>
      <team_long>Coast Guard Bears</team_long>
      <c1>28</c1>
      <c2>20</c2>
      <T>48</T>
    </visitor>
    <home>
      <id></id>
      <team_long>Quinnipiac Bobcats</team_long>
      <c1>67</c1>
      <c2>49</c2>
      <T>116</T>
    </home>
  </LINESCORE>
  <GAME_NOTES>
    <top_performers>
      <assists>
        <home>
          <player>
            <player_name>savion-lewis</player_name>
            <player_ID>4398398</player_ID>
            <ast>8</ast>
            <to>2</to>
            <min>15</min>
          </player>
        </home>
        <visitor>
          <player>
            <player_name>declan-rooney</player_name>
            <player_ID>5119075</player_ID>
            <ast>2</ast>
            <to>2</to>
            <min>18</min>
          </player>
        </visitor>
      </assists>
      <points>
        <home>
          <player>
            <player_name>matt-balanc</player_name>
            <player_ID>4398397</player_ID>
            <pts>20</pts>
            <fg>6/11</fg>
            <ft>3/3</ft>
          </player>
        </home>
        <visitor>
          <player>
            <player_name>mitch-shettles</player_name>
            <player_ID>5119077</player_ID>
            <pts>9</pts>
            <fg>3/4</fg>
            <ft>0/0</ft>
          </player>
        </visitor>
      </points>
      <rebounds>
        <home>
          <player>
            <player_name>rihards-vavers</player_name>
            <player_ID>5177139</player_ID>
            <reb>7</reb>
            <dreb>6</dreb>
            <oreb>1</oreb>
          </player>
        </home>
        <visitor>
          <player>
            <player_name>luke-farrell</player_name>
            <player_ID>5119085</player_ID>
            <reb>5</reb>
            <dreb>5</dreb>
            <oreb>0</oreb>
          </player>
        </visitor>
      </rebounds>
    </top_performers>
  </GAME_NOTES>
  <STATS>
    <visitor>
      <team>Coast Guard Bears</team>
      <starters>
        <player>
          <player_name>jordan-frazer</player_name>
          <player_jersey>23</player_jersey>
          <pos>F</pos>
          <player_ID>5180682</player_ID>
          <MIN>22</MIN>
          <FGM-A>2-7</FGM-A>
          <_3PM-A>0-3</_3PM-A>
          <FTM-A>0-0</FTM-A>
          <OREB>0</OREB>
          <DREB>4</DREB>
          <REB>4</REB>
          <AST>1</AST>
          <STL>0</STL>
          <BLK>0</BLK>
          <TO>2</TO>
          <PF>2</PF>
          <PTS>4</PTS>
        </player>
        <player>
          <player_name>cameron-brown</player_name>
          <player_jersey>45</player_jersey>
          <pos>C</pos>
          <player_ID>5119083</player_ID>
          <MIN>15</MIN>
          <FGM-A>1-6</FGM-A>
          <_3PM-A>0-0</_3PM-A>
          <FTM-A>4-4</FTM-A>
          <OREB>1</OREB>
          <DREB>0</DREB>
          <REB>1</REB>
          <AST>1</AST>
          <STL>2</STL>
          <BLK>1</BLK>
          <TO>2</TO>
          <PF>1</PF>
          <PTS>6</PTS>
        </player>
        <player>
          <player_name>elijah-parent</player_name>
          <player_jersey>15</player_jersey>
          <pos>G</pos>
          <player_ID>5119081</player_ID>
          <MIN>21</MIN>
          <FGM-A>2-7</FGM-A>
          <_3PM-A>0-1</_3PM-A>
          <FTM-A>0-0</FTM-A>
          <OREB>1</OREB>
          <DREB>1</DREB>
          <REB>2</REB>
          <AST>1</AST>
          <STL>2</STL>
          <BLK>0</BLK>
          <TO>1</TO>
          <PF>1</PF>
          <PTS>4</PTS>
        </player>
        <player>
          <player_name>mitch-shettles</player_name>
          <player_jersey>5</player_jersey>
          <pos>G</pos>
          <player_ID>5119077</player_ID>
          <MIN>12</MIN>
          <FGM-A>3-4</FGM-A>
          <_3PM-A>3-4</_3PM-A>
          <FTM-A>0-0</FTM-A>
          <OREB>0</OREB>
          <DREB>1</DREB>
          <REB>1</REB>
          <AST>1</AST>
          <STL>1</STL>
          <BLK>0</BLK>
          <TO>0</TO>
          <PF>1</PF>
          <PTS>9</PTS>
        </player>
        <player>
          <player_name>declan-rooney</player_name>
          <player_jersey>3</player_jersey>
          <pos>G</pos>
          <player_ID>5119075</player_ID>
          <MIN>18</MIN>
          <FGM-A>1-9</FGM-A>
          <_3PM-A>0-5</_3PM-A>
          <FTM-A>0-0</FTM-A>
          <OREB>0</OREB>
          <DREB>1</DREB>
          <REB>1</REB>
          <AST>2</AST>
          <STL>0</STL>
          <BLK>0</BLK>
          <TO>2</TO>
          <PF>1</PF>
          <PTS>2</PTS>
        </player>
      </starters>
      <bench>
        <player>
          <player_name>walker-corbin</player_name>
          <player_jersey>22</player_jersey>
          <pos>F</pos>
          <player_ID>5180681</player_ID>
          <MIN>16</MIN>
          <FGM-A>1-4</FGM-A>
          <_3PM-A>1-4</_3PM-A>
          <FTM-A>0-0</FTM-A>
          <OREB>0</OREB>
          <DREB>2</DREB>
          <REB>2</REB>
          <AST>0</AST>
          <STL>0</STL>
          <BLK>0</BLK>
          <TO>1</TO>
          <PF>0</PF>
          <PTS>3</PTS>
        </player>
        <player>
          <player_name>adryan-herron</player_name>
          <player_jersey>33</player_jersey>
          <pos>F</pos>
          <player_ID>5119086</player_ID>
          <MIN>11</MIN>
          <FGM-A>0-0</FGM-A>
          <_3PM-A>0-0</_3PM-A>
          <FTM-A>0-0</FTM-A>
          <OREB>1</OREB>
          <DREB>1</DREB>
          <REB>2</REB>
          <AST>0</AST>
          <STL>0</STL>
          <BLK>2</BLK>
          <TO>2</TO>
          <PF>2</PF>
          <PTS>0</PTS>
        </player>
        <player>
          <player_name>jahi-fleet</player_name>
          <player_jersey>24</player_jersey>
          <pos>F</pos>
          <player_ID>5119084</player_ID>
          <MIN>10</MIN>
          <FGM-A>0-5</FGM-A>
          <_3PM-A>0-1</_3PM-A>
          <FTM-A>0-0</FTM-A>
          <OREB>1</OREB>
          <DREB>0</DREB>
          <REB>1</REB>
          <AST>0</AST>
          <STL>0</STL>
          <BLK>0</BLK>
          <TO>1</TO>
          <PF>3</PF>
          <PTS>0</PTS>
        </player>
        <player>
          <player_name>luke-farrell</player_name>
          <player_jersey>25</player_jersey>
          <pos>G</pos>
          <player_ID>5119085</player_ID>
          <MIN>14</MIN>
          <FGM-A>2-4</FGM-A>
          <_3PM-A>0-0</_3PM-A>
          <FTM-A>2-4</FTM-A>
          <OREB>0</OREB>
          <DREB>5</DREB>
          <REB>5</REB>
          <AST>1</AST>
          <STL>0</STL>
          <BLK>0</BLK>
          <TO>1</TO>
          <PF>3</PF>
          <PTS>6</PTS>
        </player>
        <player>
          <player_name>christian-rodgers</player_name>
          <player_jersey>2</player_jersey>
          <pos>G</pos>
          <player_ID>5119082</player_ID>
          <MIN>11</MIN>
          <FGM-A>1-3</FGM-A>
          <_3PM-A>1-2</_3PM-A>
          <FTM-A>0-0</FTM-A>
          <OREB>0</OREB>
          <DREB>0</DREB>
          <REB>0</REB>
          <AST>1</AST>
          <STL>1</STL>
          <BLK>0</BLK>
          <TO>0</TO>
          <PF>1</PF>
          <PTS>3</PTS>
        </player>
        <player>
          <player_name>ben-yagey</player_name>
          <player_jersey>12</player_jersey>
          <pos>G</pos>
          <player_ID>5119080</player_ID>
          <MIN>29</MIN>
          <FGM-A>3-8</FGM-A>
          <_3PM-A>1-5</_3PM-A>
          <FTM-A>0-0</FTM-A>
          <OREB>1</OREB>
          <DREB>2</DREB>
          <REB>3</REB>
          <AST>0</AST>
          <STL>2</STL>
          <BLK>0</BLK>
          <TO>2</TO>
          <PF>2</PF>
          <PTS>7</PTS>
        </player>
        <player>
          <player_name>trevor-parks</player_name>
          <player_jersey>11</player_jersey>
          <pos>G</pos>
          <player_ID>5119079</player_ID>
          <MIN>21</MIN>
          <FGM-A>1-8</FGM-A>
          <_3PM-A>1-7</_3PM-A>
          <FTM-A>1-2</FTM-A>
          <OREB>2</OREB>
          <DREB>2</DREB>
          <REB>4</REB>
          <AST>1</AST>
          <STL>0</STL>
          <BLK>0</BLK>
          <TO>2</TO>
          <PF>3</PF>
          <PTS>4</PTS>
        </player>
      </bench>
      <totals>
        <player>
          <player_name>team</player_name>
          <player_jersey></player_jersey>
          <pos></pos>
          <player_ID>0</player_ID>
          <MIN></MIN>
          <FGM-A>17-65</FGM-A>
          <_3PM-A>7-32</_3PM-A>
          <FTM-A>7-10</FTM-A>
          <OREB>7</OREB>
          <DREB>19</DREB>
          <REB>26</REB>
          <AST>9</AST>
          <STL>8</STL>
          <BLK>3</BLK>
          <TO>16</TO>
          <PF>20</PF>
          <PTS>48</PTS>
        </player>
      </totals>
    </visitor>
    <home>
      <team>Quinnipiac Bobcats</team>
      <starters>
        <player>
          <player_name>paul-otieno</player_name>
          <player_jersey>33</player_jersey>
          <pos>F</pos>
          <player_ID>5107797</player_ID>
          <MIN>15</MIN>
          <FGM-A>4-5</FGM-A>
          <_3PM-A>0-0</_3PM-A>
          <FTM-A>3-3</FTM-A>
          <OREB>1</OREB>
          <DREB>2</DREB>
          <REB>3</REB>
          <AST>2</AST>
          <STL>1</STL>
          <BLK>0</BLK>
          <TO>0</TO>
          <PF>2</PF>
          <PTS>11</PTS>
        </player>
        <player>
          <player_name>amarri-monroe</player_name>
          <player_jersey>15</player_jersey>
          <pos>F</pos>
          <player_ID>5107321</player_ID>
          <MIN>18</MIN>
          <FGM-A>4-5</FGM-A>
          <_3PM-A>1-1</_3PM-A>
          <FTM-A>2-3</FTM-A>
          <OREB>0</OREB>
          <DREB>7</DREB>
          <REB>7</REB>
          <AST>0</AST>
          <STL>1</STL>
          <BLK>2</BLK>
          <TO>2</TO>
          <PF>1</PF>
          <PTS>11</PTS>
        </player>
        <player>
          <player_name>alexis-reyes</player_name>
          <player_jersey>0</player_jersey>
          <pos>F</pos>
          <player_ID>4708217</player_ID>
          <MIN>19</MIN>
          <FGM-A>2-3</FGM-A>
          <_3PM-A>2-3</_3PM-A>
          <FTM-A>2-2</FTM-A>
          <OREB>1</OREB>
          <DREB>5</DREB>
          <REB>6</REB>
          <AST>3</AST>
          <STL>2</STL>
          <BLK>0</BLK>
          <TO>1</TO>
          <PF>0</PF>
          <PTS>8</PTS>
        </player>
        <player>
          <player_name>savion-lewis</player_name>
          <player_jersey>3</player_jersey>
          <pos>G</pos>
          <player_ID>4398398</player_ID>
          <MIN>15</MIN>
          <FGM-A>2-2</FGM-A>
          <_3PM-A>0-0</_3PM-A>
          <FTM-A>0-0</FTM-A>
          <OREB>0</OREB>
          <DREB>1</DREB>
          <REB>1</REB>
          <AST>8</AST>
          <STL>1</STL>
          <BLK>0</BLK>
          <TO>2</TO>
          <PF>0</PF>
          <PTS>4</PTS>
        </player>
        <player>
          <player_name>matt-balanc</player_name>
          <player_jersey>2</player_jersey>
          <pos>G</pos>
          <player_ID>4398397</player_ID>
          <MIN>17</MIN>
          <FGM-A>6-11</FGM-A>
          <_3PM-A>5-9</_3PM-A>
          <FTM-A>3-3</FTM-A>
          <OREB>0</OREB>
          <DREB>0</DREB>
          <REB>0</REB>
          <AST>0</AST>
          <STL>0</STL>
          <BLK>1</BLK>
          <TO>0</TO>
          <PF>0</PF>
          <PTS>20</PTS>
        </player>
      </starters>
      <bench>
        <player>
          <player_name>rihards-vavers</player_name>
          <player_jersey>12</player_jersey>
          <pos>F</pos>
          <player_ID>5177139</player_ID>
          <MIN>16</MIN>
          <FGM-A>4-4</FGM-A>
          <_3PM-A>3-3</_3PM-A>
          <FTM-A>4-5</FTM-A>
          <OREB>1</OREB>
          <DREB>6</DREB>
          <REB>7</REB>
          <AST>0</AST>
          <STL>0</STL>
          <BLK>3</BLK>
          <TO>0</TO>
          <PF>0</PF>
          <PTS>15</PTS>
        </player>
        <player>
          <player_name>richie-springs</player_name>
          <player_jersey>1</player_jersey>
          <pos>F</pos>
          <player_ID>4592905</player_ID>
          <MIN>18</MIN>
          <FGM-A>5-8</FGM-A>
          <_3PM-A>0-0</_3PM-A>
          <FTM-A>0-1</FTM-A>
          <OREB>1</OREB>
          <DREB>3</DREB>
          <REB>4</REB>
          <AST>0</AST>
          <STL>1</STL>
          <BLK>2</BLK>
          <TO>2</TO>
          <PF>1</PF>
          <PTS>10</PTS>
        </player>
        <player>
          <player_name>jj-riggins</player_name>
          <player_jersey>23</player_jersey>
          <pos>F</pos>
          <player_ID>4432089</player_ID>
          <MIN>14</MIN>
          <FGM-A>2-4</FGM-A>
          <_3PM-A>0-1</_3PM-A>
          <FTM-A>2-2</FTM-A>
          <OREB>1</OREB>
          <DREB>5</DREB>
          <REB>6</REB>
          <AST>2</AST>
          <STL>1</STL>
          <BLK>0</BLK>
          <TO>2</TO>
          <PF>2</PF>
          <PTS>6</PTS>
        </player>
        <player>
          <player_name>daemar-kelly</player_name>
          <player_jersey>13</player_jersey>
          <pos>G</pos>
          <player_ID>5177140</player_ID>
          <MIN>17</MIN>
          <FGM-A>2-5</FGM-A>
          <_3PM-A>1-4</_3PM-A>
          <FTM-A>2-2</FTM-A>
          <OREB>0</OREB>
          <DREB>2</DREB>
          <REB>2</REB>
          <AST>1</AST>
          <STL>0</STL>
          <BLK>2</BLK>
          <TO>0</TO>
          <PF>2</PF>
          <PTS>7</PTS>
        </player>
        <player>
          <player_name>doug-young</player_name>
          <player_jersey>5</player_jersey>
          <pos>G</pos>
          <player_ID>5177138</player_ID>
          <MIN>14</MIN>
          <FGM-A>5-8</FGM-A>
          <_3PM-A>3-4</_3PM-A>
          <FTM-A>2-3</FTM-A>
          <OREB>1</OREB>
          <DREB>2</DREB>
          <REB>3</REB>
          <AST>1</AST>
          <STL>0</STL>
          <BLK>0</BLK>
          <TO>1</TO>
          <PF>1</PF>
          <PTS>15</PTS>
        </player>
        <player>
          <player_name>khaden-bennett</player_name>
          <player_jersey>4</player_jersey>
          <pos>G</pos>
          <player_ID>5177137</player_ID>
          <MIN>22</MIN>
          <FGM-A>1-6</FGM-A>
          <_3PM-A>0-5</_3PM-A>
          <FTM-A>2-2</FTM-A>
          <OREB>1</OREB>
          <DREB>6</DREB>
          <REB>7</REB>
          <AST>1</AST>
          <STL>0</STL>
          <BLK>0</BLK>
          <TO>2</TO>
          <PF>0</PF>
          <PTS>4</PTS>
        </player>
        <player>
          <player_name>nicholas-margetson</player_name>
          <player_jersey>10</player_jersey>
          <pos>G</pos>
          <player_ID>5113377</player_ID>
          <MIN>15</MIN>
          <FGM-A>1-2</FGM-A>
          <_3PM-A>0-1</_3PM-A>
          <FTM-A>3-4</FTM-A>
          <OREB>1</OREB>
          <DREB>1</DREB>
          <REB>2</REB>
          <AST>1</AST>
          <STL>1</STL>
          <BLK>0</BLK>
          <TO>1</TO>
          <PF>1</PF>
          <PTS>5</PTS>
        </player>
      </bench>
      <totals>
        <player>
          <player_name>team</player_name>
          <player_jersey></player_jersey>
          <pos></pos>
          <player_ID>0</player_ID>
          <MIN></MIN>
          <FGM-A>38-63</FGM-A>
          <_3PM-A>15-31</_3PM-A>
          <FTM-A>25-30</FTM-A>
          <OREB>8</OREB>
          <DREB>40</DREB>
          <REB>48</REB>
          <AST>19</AST>
          <STL>8</STL>
          <BLK>10</BLK>
          <TO>13</TO>
          <PF>10</PF>
          <PTS>116</PTS>
        </player>
      </totals>
    </home>
    <flagrant_fouls>None</flagrant_fouls>
    <technicals>
      <person>None</person>
    </technicals>
    <officials>
      <person>None</person>
    </officials>
    <time_of_game></time_of_game>
  </STATS>
  <ESPN_TEAM_ROSTER>
    <visitor>
      <roster_header>Coast Guard Bears Roster 2023-24</roster_header>
      <coach>Coach Kevin Jaskiewicz</coach>
      <player>
        <NO>23</NO>
        <NAME>jordan-frazer</NAME>
        <ID>5180682</ID>
        <POS>F</POS>
        <HT>6-1</HT>
        <WT>175 lbs</WT>
        <CLASS>FR</CLASS>
        <BIRTHPLACE>Columbia, SC</BIRTHPLACE>
      </player>
      <player>
        <NO>45</NO>
        <NAME>cameron-brown</NAME>
        <ID>5119083</ID>
        <POS>C</POS>
        <HT>6-8</HT>
        <WT>215 lbs</WT>
        <CLASS>JR</CLASS>
        <BIRTHPLACE>Ellicott City, MD</BIRTHPLACE>
      </player>
      <player>
        <NO>15</NO>
        <NAME>elijah-parent</NAME>
        <ID>5119081</ID>
        <POS>G</POS>
        <HT>6-2</HT>
        <WT>175 lbs</WT>
        <CLASS>SO</CLASS>
        <BIRTHPLACE>Bristol, CT</BIRTHPLACE>
      </player>
      <player>
        <NO>5</NO>
        <NAME>mitch-shettles</NAME>
        <ID>5119077</ID>
        <POS>G</POS>
        <HT>6-2</HT>
        <WT>175 lbs</WT>
        <CLASS>SO</CLASS>
        <BIRTHPLACE>New Albany, MS</BIRTHPLACE>
      </player>
      <player>
        <NO>3</NO>
        <NAME>declan-rooney</NAME>
        <ID>5119075</ID>
        <POS>G</POS>
        <HT>6-3</HT>
        <WT>185 lbs</WT>
        <CLASS>JR</CLASS>
        <BIRTHPLACE>Seattle, WA</BIRTHPLACE>
      </player>
      <player>
        <NO>22</NO>
        <NAME>walker-corbin</NAME>
        <ID>5180681</ID>
        <POS>F</POS>
        <HT>6-3</HT>
        <WT>185 lbs</WT>
        <CLASS>FR</CLASS>
        <BIRTHPLACE>Weaverville, NC</BIRTHPLACE>
      </player>
      <player>
        <NO>33</NO>
        <NAME>adryan-herron</NAME>
        <ID>5119086</ID>
        <POS>F</POS>
        <HT>6-5</HT>
        <WT>195 lbs</WT>
        <CLASS>JR</CLASS>
        <BIRTHPLACE>Saint Leonard, MD</BIRTHPLACE>
      </player>
      <player>
        <NO>24</NO>
        <NAME>jahi-fleet</NAME>
        <ID>5119084</ID>
        <POS>F</POS>
        <HT>5-10</HT>
        <WT>165 lbs</WT>
        <CLASS>SR</CLASS>
        <BIRTHPLACE>Inwood, WV</BIRTHPLACE>
      </player>
      <player>
        <NO>25</NO>
        <NAME>luke-farrell</NAME>
        <ID>5119085</ID>
        <POS>G</POS>
        <HT>6-7</HT>
        <WT>200 lbs</WT>
        <CLASS>SO</CLASS>
        <BIRTHPLACE>Ortley, SD</BIRTHPLACE>
      </player>
      <player>
        <NO>2</NO>
        <NAME>christian-rodgers</NAME>
        <ID>5119082</ID>
        <POS>G</POS>
        <HT>5-10</HT>
        <WT>170 lbs</WT>
        <CLASS>SO</CLASS>
        <BIRTHPLACE>Linwood, NJ</BIRTHPLACE>
      </player>
      <player>
        <NO>12</NO>
        <NAME>ben-yagey</NAME>
        <ID>5119080</ID>
        <POS>G</POS>
        <HT>6-1</HT>
        <WT>175 lbs</WT>
        <CLASS>JR</CLASS>
        <BIRTHPLACE>Highlands Ranch, CO</BIRTHPLACE>
      </player>
      <player>
        <NO>11</NO>
        <NAME>trevor-parks</NAME>
        <ID>5119079</ID>
        <POS>G</POS>
        <HT>6-3</HT>
        <WT>185 lbs</WT>
        <CLASS>SO</CLASS>
        <BIRTHPLACE>Oldsmar, FL</BIRTHPLACE>
      </player>
      <player>
        <NO>3</NO>
        <NAME>nate-aime</NAME>
        <ID>5180683</ID>
        <POS>F</POS>
        <HT>6-0</HT>
        <WT>175 lbs</WT>
        <CLASS>SR</CLASS>
        <BIRTHPLACE>Easton, CT</BIRTHPLACE>
      </player>
      <player>
        <NO>5</NO>
        <NAME>bryce-vanderwiere</NAME>
        <ID>5119088</ID>
        <POS>C</POS>
        <HT>6-7</HT>
        <WT>215 lbs</WT>
        <CLASS>JR</CLASS>
        <BIRTHPLACE>Schoolcraft, MI</BIRTHPLACE>
      </player>
    </visitor>
    <home>
      <roster_header>Quinnipiac Bobcats Roster 2023-24</roster_header>
      <coach>Coach Tom Pecora</coach>
      <player>
        <NO>33</NO>
        <NAME>paul-otieno</NAME>
        <ID>5107797</ID>
        <POS>F</POS>
        <HT></HT>
        <WT></WT>
        <CLASS></CLASS>
        <BIRTHPLACE></BIRTHPLACE>
      </player>
      <player>
        <NO>2</NO>
        <NAME>amarri-monroe</NAME>
        <ID>5107321</ID>
        <POS>F</POS>
        <HT>6-7</HT>
        <WT>220 lbs</WT>
        <CLASS>SR</CLASS>
        <BIRTHPLACE>Newburgh, NY</BIRTHPLACE>
      </player>
      <player>
        <NO>0</NO>
        <NAME>alexis-reyes</NAME>
        <ID>4708217</ID>
        <POS>F</POS>
        <HT></HT>
        <WT></WT>
        <CLASS></CLASS>
        <BIRTHPLACE></BIRTHPLACE>
      </player>
      <player>
        <NO>3</NO>
        <NAME>savion-lewis</NAME>
        <ID>4398398</ID>
        <POS>G</POS>
        <HT></HT>
        <WT></WT>
        <CLASS></CLASS>
        <BIRTHPLACE></BIRTHPLACE>
      </player>
      <player>
        <NO>2</NO>
        <NAME>matt-balanc</NAME>
        <ID>4398397</ID>
        <POS>G</POS>
        <HT></HT>
        <WT></WT>
        <CLASS></CLASS>
        <BIRTHPLACE></BIRTHPLACE>
      </player>
      <player>
        <NO>12</NO>
        <NAME>rihards-vavers</NAME>
        <ID>5177139</ID>
        <POS>F</POS>
        <HT></HT>
        <WT></WT>
        <CLASS></CLASS>
        <BIRTHPLACE></BIRTHPLACE>
      </player>
      <player>
        <NO>1</NO>
        <NAME>richie-springs</NAME>
        <ID>4592905</ID>
        <POS>F</POS>
        <HT></HT>
        <WT></WT>
        <CLASS></CLASS>
        <BIRTHPLACE></BIRTHPLACE>
      </player>
      <player>
        <NO>23</NO>
        <NAME>jj-riggins</NAME>
        <ID>4432089</ID>
        <POS>F</POS>
        <HT></HT>
        <WT></WT>
        <CLASS></CLASS>
        <BIRTHPLACE></BIRTHPLACE>
      </player>
      <player>
        <NO>13</NO>
        <NAME>daemar-kelly</NAME>
        <ID>5177140</ID>
        <POS>G</POS>
        <HT></HT>
        <WT></WT>
        <CLASS></CLASS>
        <BIRTHPLACE></BIRTHPLACE>
      </player>
      <player>
        <NO>5</NO>
        <NAME>doug-young</NAME>
        <ID>5177138</ID>
        <POS>G</POS>
        <HT></HT>
        <WT></WT>
        <CLASS></CLASS>
        <BIRTHPLACE></BIRTHPLACE>
      </player>
      <player>
        <NO>4</NO>
        <NAME>khaden-bennett</NAME>
        <ID>5177137</ID>
        <POS>G</POS>
        <HT></HT>
        <WT></WT>
        <CLASS></CLASS>
        <BIRTHPLACE></BIRTHPLACE>
      </player>
      <player>
        <NO>10</NO>
        <NAME>nicholas-margetson</NAME>
        <ID>5113377</ID>
        <POS>G</POS>
        <HT></HT>
        <WT></WT>
        <CLASS></CLASS>
        <BIRTHPLACE></BIRTHPLACE>
      </player>
      <player>
        <NO>22</NO>
        <NAME>elijah-taylor</NAME>
        <ID>4433210</ID>
        <POS>F</POS>
        <HT></HT>
        <WT></WT>
        <CLASS></CLASS>
        <BIRTHPLACE></BIRTHPLACE>
      </player>
      <player>
        <NO>11</NO>
        <NAME>arion-lewis</NAME>
        <ID>5108767</ID>
        <POS>G</POS>
        <HT></HT>
        <WT></WT>
        <CLASS></CLASS>
        <BIRTHPLACE></BIRTHPLACE>
      </player>
      <player>
        <NO>14</NO>
        <NAME>quinn-guth</NAME>
        <ID>4902535</ID>
        <POS>G</POS>
        <HT></HT>
        <WT></WT>
        <CLASS></CLASS>
        <BIRTHPLACE></BIRTHPLACE>
      </player>
    </home>
  </ESPN_TEAM_ROSTER>
  <ESPN_RECAP>Balanc's 20 points lead Quinnipiac over Coast Guard 116-48</ESPN_RECAP>
  <ESPN_PLAYBYPLAY></ESPN_PLAYBYPLAY>
</ESPN_EVENT>